bach_google_search_pse-0.2.5.dist-info/licenses/LICENSE
mcpccc/__init__.py
mcpccc/__main__.py
bach_google_search_pse-0.2.5.dist-info/METADATA
bach_google_search_pse-0.2.5.dist-info/WHEEL
bach_google_search_pse-0.2.5.dist-info/entry_points.txt
bach_google_search_pse-0.2.5.dist-info/top_level.txt
bach_google_search_pse-0.2.5.dist-info/RECORD
