Metadata-Version: 2.4
Name: bach-google-search-pse
Version: 0.2.5
Summary: Google 可编程搜索引擎 MCP 服务器 - 提供关键词搜索、URL内容获取和PDF解析功能
Author-email: bachstudio <bachstudio@example.com>
License: MIT
Project-URL: Homepage, https://github.com/BACH-AI-Tools/GoogleSearchPSEMCP
Project-URL: Repository, https://github.com/BACH-AI-Tools/GoogleSearchPSEMCP.git
Project-URL: Bug Reports, https://github.com/BACH-AI-Tools/GoogleSearchPSEMCP/issues
Keywords: mcp,google-search,pse,web-scraping,pdf-parser
Requires-Python: >=3.11
License-File: LICENSE
Requires-Dist: mcp[cli]>=1.12.3
Requires-Dist: requests>=2.31.0
Dynamic: license-file
